token_user_visit/__init__.py
token_user_visit/admin.py
token_user_visit/apps.py
token_user_visit/middleware.py
token_user_visit/migrations/0001_initial.py
token_user_visit/migrations/0002_alter_tokenuservisit_hash_and_more.py
token_user_visit/migrations/__init__.py
token_user_visit/models.py
token_user_visit/settings.py
django_token_user_visit-0.1.2.dist-info/LICENSE
django_token_user_visit-0.1.2.dist-info/METADATA
django_token_user_visit-0.1.2.dist-info/WHEEL
django_token_user_visit-0.1.2.dist-info/RECORD
