Metadata-Version: 2.1
Name: django-token-user-visit
Version: 0.1.2
Summary: A friendly fork of django-user-visit that supports sessions and tokens 
Home-page: https://github.com/dlondonmedina/django-token-user-visit
License: MIT
Author: Dylan Medina
Author-email: dylan@dylanmedina.com
Maintainer: Dylan Medina
Maintainer-email: dylan@dylanmedina.com
Requires-Python: >=3.8,<4.0
Classifier: Environment :: Web Environment
Classifier: Framework :: Django
Classifier: Framework :: Django :: 3.2
Classifier: Framework :: Django :: 4.1
Classifier: Framework :: Django :: 4.2
Classifier: License :: OSI Approved :: MIT License
Classifier: Operating System :: OS Independent
Classifier: Programming Language :: Python :: 3
Classifier: Programming Language :: Python :: 3.8
Classifier: Programming Language :: Python :: 3.9
Classifier: Programming Language :: Python :: 3.10
Classifier: Programming Language :: Python :: 3.11
Classifier: Programming Language :: Python :: 3 :: Only
Requires-Dist: django (>=3.2,<5.0)
Requires-Dist: user-agents (>=2.1,<3.0)
Project-URL: Documentation, https://github.com/dlondonmedina/django-token-user-visit
Project-URL: Repository, https://github.com/dlondonmedina/django-token-user-visit
